{"cameraMode":{"drawMode":0,"name":"Shaded","section":"Shading Mode"},"sceneLighting":true,"audioPlay":false,"sceneViewState":{"m_AlwaysRefresh":false,"showFog":true,"showSkybox":true,"showFlares":true,"showImageEffects":true,"showParticleSystems":true,"showVisualEffectGraphs":true,"m_FxEnabled":true},"in2DMode":false,"pivot":{"x":659.75,"y":34.75,"z":0.0},"rotation":{"x":0.3841559886932373,"y":0.02907564304769039,"z":-0.012104913592338562,"w":0.9227309226989746},"size":49.85102844238281,"orthographic":true}